spikeometric/datasets/__init__.py
spikeometric/datasets/connectivity_dataset.py
spikeometric/datasets/connectivity_generator.py
spikeometric/datasets/mexican_hat_connectivity_generator.py
spikeometric/datasets/normal_connectivity_generator.py
spikeometric/datasets/uniform_connectivity_generator.py
spikeometric/models/__init__.py
spikeometric/models/base_model.py
spikeometric/models/bernoulli_glm_model.py
spikeometric/models/poisson_glm_model.py
spikeometric/models/rectified_lnp_model.py
spikeometric/models/rectified_sa_model.py
spikeometric/models/sa_model.py
spikeometric/models/threshold_sa_model.py
spikeometric/stimulus/__init__.py
spikeometric/stimulus/base_stimulus.py
spikeometric/stimulus/loaded_stimulus.py
spikeometric/stimulus/poisson_stimulus.py
spikeometric/stimulus/regular_stimulus.py
spikeometric/stimulus/sin_stimulus.py
spikeometric-1.0.3.dist-info/WHEEL
spikeometric-1.0.3.dist-info/METADATA
spikeometric-1.0.3.dist-info/LICENSE
spikeometric-1.0.3.dist-info/RECORD
