Metadata-Version: 2.1
Name: spikeometric
Version: 1.0.3
Summary: Spikeometric is a Pytorch Geometric based framework for simulating Spiking Neural Networks using Linear Non-linear Cascade models
Home-page: https://github.com/bioAI-Oslo/Spikeometric
License: GNU General Public License v3.0
Author: Jakob Sønstebø
Author-email: jakobls16@gmail.com
Requires-Python: >=3.8,<3.12
Classifier: License :: Other/Proprietary License
Classifier: Programming Language :: Python :: 3
Classifier: Programming Language :: Python :: 3.8
Classifier: Programming Language :: Python :: 3.9
Classifier: Programming Language :: Python :: 3.10
Classifier: Programming Language :: Python :: 3.11
Requires-Dist: kiwisolver (==1.4.4)
Requires-Dist: matplotlib (>=3.7.1,<4.0.0)
Requires-Dist: networkx (>=3.0,<4.0)
Requires-Dist: numpy (<1.24)
Requires-Dist: pillow (==9.4.0)
Requires-Dist: pyparsing (>=3.1.1,<4.0.0)
Requires-Dist: pytz (==2023.3)
Requires-Dist: scipy (>=1.7.3,<2.0.0)
Requires-Dist: seaborn (>=0.12.2,<0.13.0)
Requires-Dist: tqdm (>=4.62.3,<5.0.0)
Project-URL: Documentation, https://spikeometric.readthedocs.io/en/latest/
Project-URL: Repository, https://github.com/bioAI-Oslo/Spikeometric
